python_generators-0.0.0.dist-info/METADATA
python_generators-0.0.0.dist-info/RECORD
python_generators-0.0.0.dist-info/WHEEL
python_generators-0.0.0.dist-info/entry_points.txt
python_generators-0.0.0.dist-info/top_level.txt
tay_say_test/__init__.py
