Metadata-Version: 2.1
Name: python-generators
Version: 0.0.0
Summary: A simple lib that prints out a random Taylor Swift lyric
Home-page: https://github.com/RuanHerculano/python-generators
Author: Ruan Herculano
Author-email: ruannawe@gmail.com
License: UNKNOWN
Download-URL: https://github.com/RuanHerculano/python-generators.git
Keywords: python,generators,crud generator
Platform: UNKNOWN
Classifier: Environment :: Console
Classifier: Intended Audience :: Developers
Classifier: License :: OSI Approved :: MIT License
Classifier: Operating System :: OS Independent
Classifier: Programming Language :: Python
Classifier: Programming Language :: Python :: 2
Classifier: Programming Language :: Python :: 3
Classifier: Topic :: Software Development :: Libraries :: Python Modules
